odoo10_addon_account_asset_disposal-10.0.1.0.0-py2.7-nspkg.pth
odoo/addons/account_asset_disposal/README.rst
odoo/addons/account_asset_disposal/__init__.py
odoo/addons/account_asset_disposal/__manifest__.py
odoo/addons/account_asset_disposal/i18n/es.po
odoo/addons/account_asset_disposal/migrations/10.0.1.0.0/pre-migration.py
odoo/addons/account_asset_disposal/models/__init__.py
odoo/addons/account_asset_disposal/models/account_asset_asset.py
odoo/addons/account_asset_disposal/static/description/icon.png
odoo/addons/account_asset_disposal/tests/__init__.py
odoo/addons/account_asset_disposal/tests/test_account_asset_disposal.py
odoo/addons/account_asset_disposal/views/account_asset_asset_view.xml
odoo10_addon_account_asset_disposal-10.0.1.0.0.dist-info/DESCRIPTION.rst
odoo10_addon_account_asset_disposal-10.0.1.0.0.dist-info/METADATA
odoo10_addon_account_asset_disposal-10.0.1.0.0.dist-info/RECORD
odoo10_addon_account_asset_disposal-10.0.1.0.0.dist-info/WHEEL
odoo10_addon_account_asset_disposal-10.0.1.0.0.dist-info/metadata.json
odoo10_addon_account_asset_disposal-10.0.1.0.0.dist-info/namespace_packages.txt
odoo10_addon_account_asset_disposal-10.0.1.0.0.dist-info/top_level.txt
